Workbook

Sheet Assumptions
A1: key | B1: value
A2: risk_free_rate | B2: 0.05
A3: equity_risk_premium | B3: 0.03
A4: beta | B4: 1.1
A5: pre_tax_cost_of_debt | B5: 0.045
A6: terminal_growth_rate | B6: 0.025
A7: explicit_forecast_years | B7: 10
A8: market_price | B8: 37.4

Sheet Inputs
A1: id | B1: value | C1: source_file | D1: page
A2: revenue|FY-2 | B2: 51362 | C2: 8268d305-Nike-Inc-2026-10K.pdf.txt | D2: 56
A3: pretax_income|FY-2 | B3: 6700 | C3: 8268d305-Nike-Inc-2026-10K.pdf.txt | D3: 56
A4: interest_net|FY-2 | B4: -161 | C4: 8268d305-Nike-Inc-2026-10K.pdf.txt | D4: 56
A5: tax_expense|FY-2 | B5: 1000 | C5: 8268d305-Nike-Inc-2026-10K.pdf.txt | D5: 56
A6: depreciation|FY-2 | B6: 796 | C6: 8268d305-Nike-Inc-2026-10K.pdf.txt | D6: 59
A7: capex|FY-2 | B7: 812 | C7: 8268d305-Nike-Inc-2026-10K.pdf.txt | D7: 59
A8: receivables|FY-2 | B8: 4427 | C8: aa16acd6-NKE_10K_2025.pdf.txt | D8: 58
A9: inventories|FY-2 | B9: 7519 | C9: aa16acd6-NKE_10K_2025.pdf.txt | D9: 58
A10: prepaid|FY-2 | B10: 1854 | C10: aa16acd6-NKE_10K_2025.pdf.txt | D10: 58
A11: payables|FY-2 | B11: 2851 | C11: aa16acd6-NKE_10K_2025.pdf.txt | D11: 58
A12: accrued|FY-2 | B12: 5725 | C12: aa16acd6-NKE_10K_2025.pdf.txt | D12: 58
A13: revenue|FY-1 | B13: 46309 | C13: 8268d305-Nike-Inc-2026-10K.pdf.txt | D13: 56
... A51: long_term_debt|Q_END | B51: 5893 | C51: 4a98fe77-NKE_10Q_2027.pdf | D51: 6

Sheet Historicals
A1: Label | B1: FY-2 | C1: FY-1 | D1: FY0
A2: Revenue | B2: =INDEX(Inputs!$B:$B,MATCH("revenue|FY-2",Inputs!$A:$A,0)) -> 51362 | C2: =INDEX(Inputs!$B:$B,MATCH("revenue|FY-1",Inputs!$A:$A,0)) -> 46309 | D2: =INDEX(Inputs!$B:$B,MATCH("revenue|FY0",Inputs!$A:$A,0)) -> 46398
A3: EBIT | B3: =INDEX(Inputs!$B:$B,MATCH("pretax_income|FY-2",Inputs!$A:$A,0))+INDEX(Inputs!$B:$B,MATCH("interest_net|FY-2",Inputs!$A:$A,0)) -> 6539 | C3: =INDEX(Inputs!$B:$B,MATCH("pretax_income|FY-1",Inputs!$A:$A,0))+INDEX(Inputs!$B:$B,MATCH("interest_net|FY-1",Inputs!$A:$A,0)) -> 3778 | D3: =INDEX(Inputs!$B:$B,MATCH("pretax_income|FY0",Inputs!$A:$A,0))+INDEX(Inputs!$B:$B,MATCH("interest_net|FY0",Inputs!$A:$A,0)) -> 3850
A4: Revenue growth | C4: =C2/B2-1 -> -0.098380125 | D4: =D2/C2-1 -> 0.0019218726
A5: EBIT margin | B5: =B3/B2 -> 0.12731202 | C5: =C3/C2 -> 0.081582414 | D5: =D3/D2 -> 0.082977715
A6: Effective tax rate | B6: =INDEX(Inputs!$B:$B,MATCH("tax_expense|FY-2",Inputs!$A:$A,0))/INDEX(Inputs!$B:$B,MATCH("pretax_income|FY-2",Inputs!$A:$A,0)) -> 0.14925373 | C6: =INDEX(Inputs!$B:$B,MATCH("tax_expense|FY-1",Inputs!$A:$A,0))/INDEX(Inputs!$B:$B,MATCH("pretax_income|FY-1",Inputs!$A:$A,0)) -> 0.17142857 | D6: =INDEX(Inputs!$B:$B,MATCH("tax_expense|FY0",Inputs!$A:$A,0))/INDEX(Inputs!$B:$B,MATCH("pretax_income|FY0",Inputs!$A:$A,0)) -> 0.20307692
A7: D&A % of revenue | B7: =INDEX(Inputs!$B:$B,MATCH("depreciation|FY-2",Inputs!$A:$A,0))/B2 -> 0.015497839 | C7: =INDEX(Inputs!$B:$B,MATCH("depreciation|FY-1",Inputs!$A:$A,0))/C2 -> 0.016735408 | D7: =INDEX(Inputs!$B:$B,MATCH("depreciation|FY0",Inputs!$A:$A,0))/D2 -> 0.016099832
A8: Capex % of revenue | B8: =INDEX(Inputs!$B:$B,MATCH("capex|FY-2",Inputs!$A:$A,0))/B2 -> 0.015809353 | C8: =INDEX(Inputs!$B:$B,MATCH("capex|FY-1",Inputs!$A:$A,0))/C2 -> 0.0092854521 | D8: =INDEX(Inputs!$B:$B,MATCH("capex|FY0",Inputs!$A:$A,0))/D2 -> 0.014742015
A9: NWC | B9: =INDEX(Inputs!$B:$B,MATCH("receivables|FY-2",Inputs!$A:$A,0))+INDEX(Inputs!$B:$B,MATCH("inventories|FY-2",Inputs!$A:$A,0))+INDEX(Inputs!$B:$B,MATCH("prepaid|FY-2",Inputs!$A:$A,0))-INDEX(Inputs!$B:$B,MATCH("payables|FY-2",Inputs!$A:$A,0))-INDEX(Inputs!$B:$B,MATCH("accrued|FY-2",Inputs!$A:$A,0)) -> 5224 | C9: =INDEX(Inputs!$B:$B,MATCH("receivables|FY-1",Inputs!$A:$A,0))+INDEX(Inputs!$B:$B,MATCH("inventories|FY-1",Inputs!$A:$A,0))+INDEX(Inputs!$B:$B,MATCH("prepaid|FY-1",Inputs!$A:$A,0))-INDEX(Inputs!$B:$B,MATCH("payables|FY-1",Inputs!$A:$A,0))-INDEX(Inputs!$B:$B,MATCH("accrued|FY-1",Inputs!$A:$A,0)) -> 4816 | D9: =INDEX(Inputs!$B:$B,MATCH("receivables|FY0",Inputs!$A:$A,0))+INDEX(Inputs!$B:$B,MATCH("inventories|FY0",Inputs!$A:$A,0))+INDEX(Inputs!$B:$B,MATCH("prepaid|FY0",Inputs!$A:$A,0))-INDEX(Inputs!$B:$B,MATCH("payables|FY0",Inputs!$A:$A,0))-INDEX(Inputs!$B:$B,MATCH("accrued|FY0",Inputs!$A:$A,0)) -> 5884
A10: NWC % of revenue | B10: =B9/B2 -> 0.10170943 | C10: =C9/C2 -> 0.10399706 | D10: =D9/D2 -> 0.12681581
A11: Net investment | C11: =INDEX(Inputs!$B:$B,MATCH("capex|FY-1",Inputs!$A:$A,0))-INDEX(Inputs!$B:$B,MATCH("depreciation|FY-1",Inputs!$A:$A,0))+(C9-B9) -> -753 | D11: =INDEX(Inputs!$B:$B,MATCH("capex|FY0",Inputs!$A:$A,0))-INDEX(Inputs!$B:$B,MATCH("depreciation|FY0",Inputs!$A:$A,0))+(D9-C9) -> 1005
A13: Avg EBIT margin | B13: =AVERAGE(B5:D5) -> 0.097290716
A14: Avg effective tax rate | B14: =AVERAGE(B6:D6) -> 0.17458641
A15: Avg D&A % of revenue | B15: =AVERAGE(B7:D7) -> 0.016111026
A16: Avg capex % of revenue | B16: =AVERAGE(B8:D8) -> 0.01327894
A17: Avg NWC % of revenue | B17: =AVERAGE(B10:D10) -> 0.11084077
A18: Revenue CAGR | B18: =POWER(D2/B2,1/2)-1 -> -0.049551331
A19: LTM revenue | B19: =D2+INDEX(Inputs!$B:$B,MATCH("revenue|YTD_CUR",Inputs!$A:$A,0))-INDEX(Inputs!$B:$B,MATCH("revenue|YTD_PRI",Inputs!$A:$A,0)) -> 45891

Sheet WACC
A1: Label | B1: Value
A2: Cost of equity | B2: =Assumptions!$B$2+Assumptions!$B$4*Assumptions!$B$3 -> 0.083
A3: After-tax cost of debt | B3: =Assumptions!$B$5*(1-Historicals!$B$14) -> 0.037143612
A4: Market cap | B4: =Assumptions!$B$8*INDEX(Inputs!$B:$B,MATCH("diluted_shares|YTD_CUR",Inputs!$A:$A,0)) -> 55509.08
A5: Debt | B5: =INDEX(Inputs!$B:$B,MATCH("notes_payable|Q_END",Inputs!$A:$A,0))+INDEX(Inputs!$B:$B,MATCH("current_ltd|Q_END",Inputs!$A:$A,0))+INDEX(Inputs!$B:$B,MATCH("long_term_debt|Q_END",Inputs!$A:$A,0)) -> 7893
A6: Equity weight | B6: =B4/(B4+B5) -> 0.87550882
A7: Debt weight | B7: =B5/(B4+B5) -> 0.12449118
A8: WACC | B8: =B6*B2+B7*B3 -> 0.077291284

Sheet DCF
A1: Label | B1: 1 | C1: 2 | D1: 3 | E1: 4 | F1: 5 | G1: 6 | H1: 7 | I1: 8 | J1: 9 | K1: 10
A2: Revenue growth | B2: =Historicals!$B$18+(Assumptions!$B$6-Historicals!$B$18)*(B$1-1)/(Assumptions!$B$7-1) -> -0.049551331 | C2: =Historicals!$B$18+(Assumptions!$B$6-Historicals!$B$18)*(C$1-1)/(Assumptions!$B$7-1) -> -0.041267849 | D2: =Historicals!$B$18+(Assumptions!$B$6-Historicals!$B$18)*(D$1-1)/(Assumptions!$B$7-1) -> -0.032984368 | E2: =Historicals!$B$18+(Assumptions!$B$6-Historicals!$B$18)*(E$1-1)/(Assumptions!$B$7-1) -> -0.024700887 | F2: =Historicals!$B$18+(Assumptions!$B$6-Historicals!$B$18)*(F$1-1)/(Assumptions!$B$7-1) -> -0.016417406 | G2: =Historicals!$B$18+(Assumptions!$B$6-Historicals!$B$18)*(G$1-1)/(Assumptions!$B$7-1) -> -0.0081339247 | H2: =Historicals!$B$18+(Assumptions!$B$6-Historicals!$B$18)*(H$1-1)/(Assumptions!$B$7-1) -> 0.00014955647 | I2: =Historicals!$B$18+(Assumptions!$B$6-Historicals!$B$18)*(I$1-1)/(Assumptions!$B$7-1) -> 0.0084330376 | ... K2: =Historicals!$B$18+(Assumptions!$B$6-Historicals!$B$18)*(K$1-1)/(Assumptions!$B$7-1) -> 0.025
A3: Revenue | B3: =Historicals!$B$19*(1+B2) -> 43617.04 | C3: =B3*(1+C2) -> 41817.058 | D3: =C3*(1+D2) -> 40437.749 | E3: =D3*(1+E2) -> 39438.901 | F3: =E3*(1+F2) -> 38791.416 | G3: =F3*(1+G2) -> 38475.89 | H3: =G3*(1+H2) -> 38481.644 | I3: =H3*(1+I2) -> 38806.161 | J3: =I3*(1+J2) -> 39454.865 | K3: =J3*(1+K2) -> 40441.237
A4: EBIT | B4: =Historicals!$B$13*B3 -> 4243.5331 | C4: =Historicals!$B$13*C3 -> 4068.4116 | D4: =Historicals!$B$13*D3 -> 3934.2176 | E4: =Historicals!$B$13*E3 -> 3837.0389 | F4: =Historicals!$B$13*F3 -> 3774.0447 | G4: =Historicals!$B$13*G3 -> 3743.3469 | H4: =Historicals!$B$13*H3 -> 3743.9067 | I4: =Historicals!$B$13*I3 -> 3775.4792 | ... K4: =Historicals!$B$13*K3 -> 3934.5569
A5: NOPAT | B5: =B4*(1-Historicals!$B$14) -> 3502.6699 | C5: =C4*(1-Historicals!$B$14) -> 3358.1222 | D5: =D4*(1-Historicals!$B$14) -> 3247.3567 | E5: =E4*(1-Historicals!$B$14) -> 3167.1441 | F5: =F4*(1-Historicals!$B$14) -> 3115.1478 | G5: =G4*(1-Historicals!$B$14) -> 3089.8094 | H5: =H4*(1-Historicals!$B$14) -> 3090.2715 | I5: =I4*(1-Historicals!$B$14) -> 3116.3319 | ... K5: =K4*(1-Historicals!$B$14) -> 3247.6368
A6: Capex | B6: =Historicals!$B$16*B3 -> 579.18806 | C6: =Historicals!$B$16*C3 -> 555.28621 | D6: =Historicals!$B$16*D3 -> 536.97045 | E6: =Historicals!$B$16*E3 -> 523.7068 | F6: =Historicals!$B$16*F3 -> 515.10889 | G6: =Historicals!$B$16*G3 -> 510.91904 | H6: =Historicals!$B$16*H3 -> 510.99545 | I6: =Historicals!$B$16*I3 -> 515.30469 | ... K6: =Historicals!$B$16*K3 -> 537.01676
A7: D&A | B7: =Historicals!$B$15*B3 -> 702.71527 | C7: =Historicals!$B$15*C3 -> 673.71572 | D7: =Historicals!$B$15*D3 -> 651.49364 | E7: =Historicals!$B$15*E3 -> 635.40117 | F7: =Historicals!$B$15*F3 -> 624.96953 | G7: =Historicals!$B$15*G3 -> 619.88607 | H7: =Historicals!$B$15*H3 -> 619.97878 | I7: =Historicals!$B$15*I3 -> 625.20708 | ... K7: =Historicals!$B$15*K3 -> 651.54983
A8: NWC | B8: =Historicals!$B$17*B3 -> 4834.5463 | C8: =Historicals!$B$17*C3 -> 4635.0349 | D8: =Historicals!$B$17*D3 -> 4482.1512 | E8: =Historicals!$B$17*E3 -> 4371.4381 | F8: =Historicals!$B$17*F3 -> 4299.6705 | G8: =Historicals!$B$17*G3 -> 4264.6973 | H8: =Historicals!$B$17*H3 -> 4265.3351 | I8: =Historicals!$B$17*I3 -> 4301.3048 | ... K8: =Historicals!$B$17*K3 -> 4482.5378
A9: Change in NWC | B9: =B8-Historicals!$B$17*Historicals!$B$19 -> -252.04749 | C9: =C8-B8 -> -199.51133 | D9: =D8-C8 -> -152.8837 | E9: =E8-D8 -> -110.71311 | F9: =F8-E8 -> -71.767674 | G9: =G8-F8 -> -34.973196 | H9: =H8-G8 -> 0.63781307 | I9: =I8-H8 -> 35.969731 | J9: =J8-I8 -> 71.902843 | K9: =K8-J8 -> 109.33019
A10: Net investment | B10: =B6-B7+B9 -> -375.5747 | C10: =C6-C7+C9 -> -317.94084 | D10: =D6-D7+D9 -> -267.40689 | E10: =E6-E7+E9 -> -222.40748 | F10: =F6-F7+F9 -> -181.62831 | G10: =G6-G7+G9 -> -143.94023 | H10: =H6-H7+H9 -> -108.34552 | I10: =I6-I7+I9 -> -73.932662 | ... K10: =K6-K7+K9 -> -5.2028771
A11: Free cash flow | B11: =B5-B10 -> 3878.2446 | C11: =C5-C10 -> 3676.063 | D11: =D5-D10 -> 3514.7636 | E11: =E5-E10 -> 3389.5516 | F11: =F5-F10 -> 3296.7761 | G11: =G5-G10 -> 3233.7496 | H11: =H5-H10 -> 3198.617 | I11: =I5-I10 -> 3190.2645 | ... K11: =K5-K10 -> 3252.8396
A12: Discount factor | B12: =1/POWER(1+WACC!$B$8,B$1) -> 0.92825405 | C12: =1/POWER(1+WACC!$B$8,C$1) -> 0.86165559 | D12: =1/POWER(1+WACC!$B$8,D$1) -> 0.79983529 | E12: =1/POWER(1+WACC!$B$8,E$1) -> 0.74245035 | F12: =1/POWER(1+WACC!$B$8,F$1) -> 0.68918255 | G12: =1/POWER(1+WACC!$B$8,G$1) -> 0.63973649 | H12: =1/POWER(1+WACC!$B$8,H$1) -> 0.59383799 | I12: =1/POWER(1+WACC!$B$8,I$1) -> 0.55123252 | ... K12: =1/POWER(1+WACC!$B$8,K$1) -> 0.47497258
A13: PV of FCF | B13: =B11*B12 -> 3599.9962 | C13: =C11*C12 -> 3167.5003 | D13: =D11*D12 -> 2811.2319 | E13: =E11*E12 -> 2516.5737 | F13: =F11*F12 -> 2272.0805 | G13: =G11*G12 -> 2068.7476 | H13: =H11*H12 -> 1899.4603 | I13: =I11*I12 -> 1758.5776 | ... K13: =K11*K12 -> 1545.0096
A15: Sum of PV of FCF | B15: =SUM(B13:K13) -> 23280.794
A16: Terminal value | B16: =K11*(1+Assumptions!$B$6)/(WACC!$B$8-Assumptions!$B$6) -> 63761.307
A17: PV of terminal value | B17: =B16*K12 -> 30284.873
A18: Enterprise value | B18: =B15+B17 -> 53565.667
A19: Cash | B19: =INDEX(Inputs!$B:$B,MATCH("cash|FY0",Inputs!$A:$A,0))+INDEX(Inputs!$B:$B,MATCH("short_term_investments|FY0",Inputs!$A:$A,0)) -> 9027
A20: Debt | B20: =INDEX(Inputs!$B:$B,MATCH("notes_payable|FY0",Inputs!$A:$A,0))+INDEX(Inputs!$B:$B,MATCH("current_ltd|FY0",Inputs!$A:$A,0))+INDEX(Inputs!$B:$B,MATCH("long_term_debt|FY0",Inputs!$A:$A,0)) -> 7942
A21: Equity value | B21: =B18+B19-B20 -> 54650.667
A22: Diluted shares | B22: =INDEX(Inputs!$B:$B,MATCH("diluted_shares|YTD_CUR",Inputs!$A:$A,0)) -> 1484.2
A23: Value per share | B23: =B21/B22 -> 36.821632
A24: Market price | B24: =Assumptions!$B$8 -> 37.4
A25: Upside | B25: =B23/B24-1 -> -0.015464376
